pyfory/__init__.pxd
pyfory/__init__.py
pyfory/_fory.py
pyfory/_registry.py
pyfory/_serializer.py
pyfory/_struct.py
pyfory/_util.pxd
pyfory/_util.pyx
pyfory/_util.so
pyfory/buffer.py
pyfory/codegen.py
pyfory/error.py
pyfory/policy.py
pyfory/resolver.py
pyfory/serialization.pyx
pyfory/serialization.so
pyfory/serializer.py
pyfory/type.py
pyfory/util.py
pyfory/format/__init__.py
pyfory/format/_format.pyx
pyfory/format/_format.so
pyfory/format/columnar.py
pyfory/format/encoder.py
pyfory/format/infer.py
pyfory/format/schema.py
pyfory/includes/__init__.pxd
pyfory/includes/libabsl.pxd
pyfory/includes/libformat.pxd
pyfory/includes/libserialization.pxd
pyfory/includes/libutil.pxd
pyfory/lib/__init__.pxd
pyfory/lib/__init__.py
pyfory/lib/collection.py
pyfory/lib/mmh3/__init__.pxd
pyfory/lib/mmh3/__init__.py
pyfory/lib/mmh3/mmh3.pxd
pyfory/lib/mmh3/mmh3.pyx
pyfory/lib/mmh3/mmh3.so
pyfory/meta/__init__.py
pyfory/meta/meta_compressor.py
pyfory/meta/metastring.py
pyfory/meta/test_meta_compressor.py
pyfory/meta/typedef.py
pyfory/meta/typedef_decoder.py
pyfory/meta/typedef_encoder.py
pyfory-0.14.1.dist-info/METADATA
pyfory-0.14.1.dist-info/WHEEL
pyfory-0.14.1.dist-info/top_level.txt
pyfory-0.14.1.dist-info/RECORD
