Metadata-Version: 2.4
Name: pyfory
Version: 0.14.1
Summary: Apache Fory™ is a blazingly fast multi-language serialization framework powered by jit and zero-copy
Author-email: chaokunyang <shawn.ck.yang@gmail.com>
Maintainer-email: "https://github.com/chaokunyang" <shawn.ck.yang@gmail.com>
Keywords: fory,serialization,multi-language,fast,row-format,jit,codegen,polymorphic,zero-copy
Classifier: License :: OSI Approved :: Apache Software License
Classifier: Development Status :: 5 - Production/Stable
Classifier: Programming Language :: Python :: 3.8
Classifier: Programming Language :: Python :: 3.9
Classifier: Programming Language :: Python :: 3.10
Classifier: Programming Language :: Python :: 3.11
Classifier: Programming Language :: Python :: 3.12
Classifier: Programming Language :: Python :: 3.13
Classifier: Programming Language :: Python :: Implementation :: CPython
Provides-Extra: format
Requires-Dist: pyarrow; extra == "format"
Provides-Extra: all
Requires-Dist: pyarrow; extra == "all"
Provides-Extra: dev
Requires-Dist: ruff; extra == "dev"
